setup.py
atomix_base.pyi
atomix_base.cpython-313t-x86_64-linux-gnu.so
atomix_base-0.1.5.dist-info/WHEEL
atomix_base-0.1.5.dist-info/METADATA
atomix_base-0.1.5.dist-info/RECORD
atomix_base-0.1.5.dist-info/top_level.txt
atomix_base-0.1.5.dist-info/licenses/LICENSE
